pyups/__init__.py
pyups/client.py
pyups/pickup.py
pyups/rates.py
pyups/shipping.py
pyups/tracking.py
pyups/typings.py
py_ups_rest-0.0.5.dist-info/LICENSE
py_ups_rest-0.0.5.dist-info/METADATA
py_ups_rest-0.0.5.dist-info/WHEEL
py_ups_rest-0.0.5.dist-info/top_level.txt
py_ups_rest-0.0.5.dist-info/RECORD
